.README.txt.swp
.hgignore
.hgtags
ABOUT.txt
HISTORY.txt
LICENSE.txt
MANIFEST.in
README.txt
moai.wsgi
settings.ini
setup.py
MOAI.egg-info/PKG-INFO
MOAI.egg-info/SOURCES.txt
MOAI.egg-info/dependency_links.txt
MOAI.egg-info/entry_points.txt
MOAI.egg-info/not-zip-safe
MOAI.egg-info/requires.txt
MOAI.egg-info/top_level.txt
moai/__init__.py
moai/database.py
moai/error.py
moai/example.py
moai/interfaces.py
moai/metadata.py
moai/oai.py
moai/server.py
moai/test.py
moai/tools.py
moai/utils.py
moai/wsgi.py
moai/metadata/__init__.py
moai/metadata/dare_didl.py
moai/metadata/didl.py
moai/metadata/mods.py
moai/metadata/oaidc.py
moai/provider/__init__.py
moai/provider/fedora.py
moai/provider/file.py
moai/provider/list.py
moai/provider/oai.py