Metadata-Version: 1.1
Name: MOAI
Version: 2.0.0
Summary: MOAI, A Open Access Server Platform for Institutional Repositories
Home-page: http://infrae.com/products/moai
Author: Infrae
Author-email: info@infrae.com
License: BSD
Platform: UNKNOWN
Classifier: Development Status :: 5 - Production/Stable
Classifier: Programming Language :: Python
Classifier: License :: OSI Approved :: BSD License
Classifier: Topic :: Software Development :: Libraries :: Python Modules
Classifier: Environment :: Web Environment
